dapi2/__init__.py
dapi2/_version.py
dapi2/common.py
dapi2/dapi2.py
dapi2/derror.py
dapi2/errors.xml
dapi2/signal.py
dapi2/dboard/__init__.py
dapi2/dboard/analoginput.py
dapi2/dboard/base.py
dapi2/dboard/common.py
dapi2/dboard/debug.py
dapi2/dboard/factory.py
dapi2/dboard/generic.py
dapi2/dboard/mb30.py
dapi2/dboard/mb60.py
dapi2/dboard/mb92.py
dapi2/dboard/workspace.py
dapi2/dcom/__init__.py
dapi2/dcom/base.py
dapi2/dcom/demu.py
dapi2/dcom/dserial.py
dapi2/dcom/dsocket.py
dapi2/dmsg/__init__.py
dapi2/dmsg/common.py
dapi2/dmsg/message.py
dapi2/dmsg/reader.py
dapi2/dmsg/writer.py
dapi2/dreg/__init__.py
dapi2/dreg/base.py
dapi2/dreg/container.py
dapi2/dreg/group.py
dapi2/dreg/reader.py
dapi2/dreg/register.py
dapi2/dreg/regs.xml
dapi2/dreg/dev/__init__.py
dapi2/dreg/dev/dev.py
demu/DEmuBaseBoard.py
demu/DEmuBaseMotor.py
demu/DEmuPPA.py
demu/__init__.py
PyDapi2-0.6.3.dist-info/LICENSE
PyDapi2-0.6.3.dist-info/METADATA
PyDapi2-0.6.3.dist-info/WHEEL
PyDapi2-0.6.3.dist-info/top_level.txt
PyDapi2-0.6.3.dist-info/RECORD
