Metadata-Version: 2.1
Name: PyDapi2
Version: 0.6.3
Summary: The PyDapi2 library offers a Python implementation of the Dassym API version 2.
Home-page: https://github.com/dassym/PyDapi2
Author: Fabrice Voillat
Author-email: dev@dassym.com
Keywords: Dassym,motor,api,dapi
Classifier: Programming Language :: Python :: 3
Classifier: Operating System :: OS Independent
Requires-Python: >=3.7
License-File: LICENSE
Requires-Dist: lxml
